rococo/__init__.py
rococo/exceptions.py
rococo/models/__init__.py
rococo/models/attachment.py
rococo/models/email.py
rococo/models/email_address.py
rococo/models/enums.py
rococo/parsers/__init__.py
rococo/parsers/email/__init__.py
rococo/parsers/email/attachment_parser.py
rococo/parsers/email/body_parser.py
rococo/parsers/email/email_encodings.py
rococo/parsers/email/header_parser.py
rococo/parsers/email/message_parser.py
rococo/parsers/email/parser.py
rococo_email_parser-1.0.0.dist-info/LICENSE
rococo_email_parser-1.0.0.dist-info/METADATA
rococo_email_parser-1.0.0.dist-info/WHEEL
rococo_email_parser-1.0.0.dist-info/top_level.txt
rococo_email_parser-1.0.0.dist-info/RECORD
