Metadata-Version: 2.2
Name: rococo-email-parser
Version: 1.0.0
Summary: A Python library to parse emails
Home-page: https://github.com/EcorRouge/rococo-email-parser
Author: Mikhail Burilov
Author-email: burilovmv@gmail.com
License: MIT
Requires-Python: >=3.10
License-File: LICENSE
Requires-Dist: pydantic<3.0.0,>=2.1.0
Requires-Dist: python-dateutil<3.0.0,>=2.1.0
Requires-Dist: beautifulsoup4==4.12.2
Requires-Dist: chardet==5.2.0
Dynamic: author
Dynamic: author-email
Dynamic: description
Dynamic: description-content-type
Dynamic: home-page
Dynamic: license
Dynamic: requires-dist
Dynamic: requires-python
Dynamic: summary
